{
    "6.7.3":{
        "beat_baseoffset":70555872,
        "deck1":280,
        "deck2":288,
        "bar":7704,
        "beat":7708,
        "master_bpm":{
            "offsets":[
                70558960,
                24,
                272,
                0,
                112
            ],
            "final_offset":344
        },
        "masterdeck_index":{
            "offsets":[
                70555872,
                144
            ],
            "final_offset":412
        }
    },
    "6.7.7":{
        "beat_baseoffset":71021136,
        "deck1":288,
        "deck2":296,
        "bar":7704,
        "beat":7708,
        "master_bpm":{
            "offsets":[
                71024224,
                40,
                520,
                472
            ],
            "final_offset":320
        },
        "masterdeck_index":{
            "offsets":[
                71021136,
                24,
                1824
            ],
            "final_offset":4184
        }
    },
    "6.7.4":{
        "beat_baseoffset":70853984,
        "deck1":288,
        "deck2":296,
        "bar":7704,
        "beat":7708,
        "master_bpm":{
            "offsets":[
                70566024,
                232,
                448,
                0
            ],
            "final_offset":2888
        },
        "masterdeck_index":{
            "offsets":[
                70857776,
                0,
                88,
                0,
                1328,
                128
            ],
            "final_offset":324
        }
    },
    "6.8.2":{
        "beat_baseoffset":71284624,
        "deck1":288,
        "deck2":296,
        "bar":7704,
        "beat":7708,
        "master_bpm":{
            "offsets":[
                71287712,
                24,
                248,
                0
            ],
            "final_offset":296
        },
        "masterdeck_index":{
            "offsets":[
                70884488,
                32,
                632
            ],
            "final_offset":3608
        }
    }
}
